django_database_task/__init__.py
django_database_task/admin.py
django_database_task/apps.py
django_database_task/backends.py
django_database_task/executor.py
django_database_task/models.py
django_database_task/urls.py
django_database_task/views.py
django_database_task/cloudtasks/__init__.py
django_database_task/cloudtasks/auth.py
django_database_task/cloudtasks/backend.py
django_database_task/cloudtasks/detection.py
django_database_task/locale/ja/LC_MESSAGES/django.mo
django_database_task/locale/ja/LC_MESSAGES/django.po
django_database_task/management/__init__.py
django_database_task/management/commands/__init__.py
django_database_task/management/commands/purge_completed_database_tasks.py
django_database_task/management/commands/run_database_tasks.py
django_database_task/migrations/0001_initial.py
django_database_task/migrations/__init__.py
django_database_task-0.2.3.dist-info/licenses/LICENSE
django_database_task-0.2.3.dist-info/METADATA
django_database_task-0.2.3.dist-info/WHEEL
django_database_task-0.2.3.dist-info/top_level.txt
django_database_task-0.2.3.dist-info/RECORD
