Metadata-Version: 2.4
Name: django-database-task
Version: 0.2.3
Summary: A database-backed task queue backend for Django 6.0's built-in task framework
Author-email: Shinya Okano <tokibito@gmail.com>
Maintainer-email: Shinya Okano <tokibito@gmail.com>
License-Expression: MIT
Project-URL: Homepage, https://github.com/tokibito/django-database-task
Project-URL: Repository, https://github.com/tokibito/django-database-task
Project-URL: Issues, https://github.com/tokibito/django-database-task/issues
Keywords: django,task,queue,background,database,async
Classifier: Development Status :: 3 - Alpha
Classifier: Environment :: Web Environment
Classifier: Framework :: Django
Classifier: Framework :: Django :: 6.0
Classifier: Intended Audience :: Developers
Classifier: Operating System :: OS Independent
Classifier: Programming Language :: Python
Classifier: Programming Language :: Python :: 3
Classifier: Programming Language :: Python :: 3.12
Classifier: Programming Language :: Python :: 3.13
Classifier: Programming Language :: Python :: 3.14
Classifier: Topic :: Software Development :: Libraries :: Python Modules
Requires-Python: >=3.12
License-File: LICENSE
Requires-Dist: Django>=6.0
Provides-Extra: cloudtasks
Requires-Dist: google-cloud-tasks>=2.0.0; extra == "cloudtasks"
Requires-Dist: google-auth>=2.0.0; extra == "cloudtasks"
Provides-Extra: dev
Requires-Dist: pytest>=7.0; extra == "dev"
Requires-Dist: pytest-django>=4.5; extra == "dev"
Requires-Dist: ruff>=0.8; extra == "dev"
Dynamic: license-file
